lica/__init__.py
lica/_version.py
lica/cli.py
lica/csv.py
lica/jinja2.py
lica/misc.py
lica/sqlite.py
lica/tabulate.py
lica/typing.py
lica/validators.py
lica/asyncio/__init__.py
lica/asyncio/cli.py
lica/asyncio/photometer/__init__.py
lica/asyncio/photometer/payload.py
lica/asyncio/photometer/photinfo.py
lica/asyncio/photometer/photometer.py
lica/asyncio/photometer/protocol.py
lica/lab/__init__.py
lica/lab/types.py
lica/lab/ndfilters/ND-0.5-Transmittance-dup@1nm.ecsv
lica/lab/ndfilters/ND-0.5-Transmittance@1nm.ecsv
lica/lab/ndfilters/ND-1.0-Transmittance@1nm.ecsv
lica/lab/ndfilters/__init__.py
lica/lab/photodiode/PIN-10D-Responsivity-Cross-Calibrated@1nm.ecsv
lica/lab/photodiode/PIN-10D-Responsivity-Interpolated@1nm.ecsv
lica/lab/photodiode/S2281-01-Responsivity-Interpolated@1nm.ecsv
lica/lab/photodiode/__init__.py
lica/raw/__init__.py
lica/raw/analyzer/__init__.py
lica/raw/analyzer/image.py
lica/raw/loader/__init__.py
lica/raw/loader/abstract.py
lica/raw/loader/constants.py
lica/raw/loader/exif.py
lica/raw/loader/factory.py
lica/raw/loader/fits.py
lica/raw/loader/roi.py
lica/raw/loader/simulation.py
lica/sqlalchemy/__init__.py
lica/sqlalchemy/metadata.py
lica/sqlalchemy/view.py
lica/sqlalchemy/asyncio/__init__.py
lica/sqlalchemy/asyncio/dbase.py
lica/sqlalchemy/asyncio/model.py
lica/sqlalchemy/noasync/__init__.py
lica/sqlalchemy/noasync/dbase.py
lica/sqlalchemy/noasync/model.py
lica/textual/__init__.py
lica/textual/argparse.py
lica/textual/logging.py
lica/textual/widgets/__init__.py
lica/textual/widgets/about.py
lica/textual/widgets/label.py
lica-3.0.7.dist-info/licenses/LICENSE
lica-3.0.7.dist-info/METADATA
lica-3.0.7.dist-info/WHEEL
lica-3.0.7.dist-info/top_level.txt
lica-3.0.7.dist-info/RECORD
